llmflows/__init__.py
llmflows/callbacks/__init__.py
llmflows/callbacks/async_base_callback.py
llmflows/callbacks/async_functional_callback.py
llmflows/callbacks/base_callback.py
llmflows/callbacks/functional_callback.py
llmflows/flows/__init__.py
llmflows/flows/async_base_flow.py
llmflows/flows/async_base_flowstep.py
llmflows/flows/async_chat_flowstep.py
llmflows/flows/async_flow.py
llmflows/flows/async_flowstep.py
llmflows/flows/base_flow.py
llmflows/flows/base_flowstep.py
llmflows/flows/chat_flowstep.py
llmflows/flows/flow.py
llmflows/flows/flowstep.py
llmflows/flows/functional_flowstep.py
llmflows/flows/vectorstore_flowstep.py
llmflows/llms/__init__.py
llmflows/llms/azure_openai.py
llmflows/llms/azure_openai_chat.py
llmflows/llms/chat_llm.py
llmflows/llms/claude_chat.py
llmflows/llms/embeddings.py
llmflows/llms/llm.py
llmflows/llms/llm_utils.py
llmflows/llms/message_history.py
llmflows/llms/openai.py
llmflows/llms/openai_chat.py
llmflows/llms/openai_embeddings.py
llmflows/llms/palm.py
llmflows/llms/palm_chat.py
llmflows/prompts/__init__.py
llmflows/prompts/prompt_template.py
llmflows/vectorstores/__init__.py
llmflows/vectorstores/pinecone.py
llmflows/vectorstores/vector_doc.py
llmflows/vectorstores/vector_store.py
llmflows-0.2.1.dist-info/LICENSE
llmflows-0.2.1.dist-info/METADATA
llmflows-0.2.1.dist-info/WHEEL
llmflows-0.2.1.dist-info/top_level.txt
llmflows-0.2.1.dist-info/RECORD
