Metadata-Version: 2.1
Name: llmflows
Version: 0.2.1
Summary: LLMFlows - Simple, Explicit and Transparent LLM Apps
Author: Stoyan Stoyanov
Project-URL: Homepage, https://github.com/stoyan-stoyanov/llmflows
Project-URL: github, https://github.com/stoyan-stoyanov/llmflows
Classifier: Programming Language :: Python :: 3
Classifier: License :: OSI Approved :: MIT License
Classifier: Operating System :: OS Independent
Requires-Python: >=3.9
License-File: LICENSE
Requires-Dist: anthropic ==0.3.11
Requires-Dist: aiohttp
Requires-Dist: openai ==0.28.1
Requires-Dist: tiktoken ==0.5.1
Requires-Dist: pinecone-client ==2.2.4
Requires-Dist: urllib3 ==1.26.17
Requires-Dist: google-generativeai ==0.2.1
